setup.py
esl/__init__.py
esl/eslast.py
esl/eslgenerator.py
esl/esllexer.py
esl/eslyacc.py
esl/formatter.py
esl/parsetab.py
esl.egg-info/PKG-INFO
esl.egg-info/SOURCES.txt
esl.egg-info/dependency_links.txt
esl.egg-info/entry_points.txt
esl.egg-info/requires.txt
esl.egg-info/top_level.txt