Metadata-Version: 1.0
Name: esl
Version: 0.5.0
Summary: eva shell language for eva-shell
Home-page: UNKNOWN
Author: detailyang
Author-email: detailyang@gmail.com
License: MIT License
Keywords: esl,eva-shell-language
Platform: any
